{
  "tet-mesh": "dragon.veg",
  "surface-mesh": "dragon.obj",
  "fixed-vertices": [
    {
      "filename": "dragon-fixed.txt",
      "movement": [
        0,
        0,
        0
      ],
      "coeff": 1e5
    }
  ],
  "external-objects": [],
  "g": [
    0,
    -9.81,
    0
  ],
  "init-vel": [
    0,
    0,
    0
  ],
  "init-disp": [
    0,
    0,
    0
  ],
  "scale": 1.0,
  "timestep": 0.004,
  "num-timestep": 2000,
  "damping-params": [
    0,
    0
  ],
  "sim-type": "static",
  "contact-stiffness": -1,
  "contact-sample": 6,
  "contact-friction-coeff": 0.3,
  "contact-vel-eps": 1e-5,
  "attachment-stiffness": 1e5,
  "solver-eps": 1e-6,
  "solver-max-iter": 300,
  "elastic-material": "stable-neo",
  "dump-interval": 10,
  "output": "static.obj"
}